Weighted_Combination/README.txt
Weighted_Combination/Weighted_Combination.py
Weighted_Combination/Weighted_Combination.spec
Weighted_Combination/__init__.py
Weighted_Combination/build/Weighted_Combination/Analysis-00.toc
Weighted_Combination/build/Weighted_Combination/COLLECT-00.toc
Weighted_Combination/build/Weighted_Combination/EXE-00.toc
Weighted_Combination/build/Weighted_Combination/PKG-00.toc
Weighted_Combination/build/Weighted_Combination/PYZ-00.pyz
Weighted_Combination/build/Weighted_Combination/PYZ-00.toc
Weighted_Combination/build/Weighted_Combination/Weighted_Combination.exe
Weighted_Combination/build/Weighted_Combination/Weighted_Combination.pkg
Weighted_Combination/build/Weighted_Combination/base_library.zip
Weighted_Combination/build/Weighted_Combination/warn-Weighted_Combination.txt
Weighted_Combination/build/Weighted_Combination/xref-Weighted_Combination.html
Weighted_Combination/test files/20Percent.dat
Weighted_Combination/test files/60Percent.dat
Weighted_Combination/test files/80Percent.dat
Weighted_Combination/test files/FullyAmorphous.dat
Weighted_Combination/test files/FullyCrystalline.dat
weighted_combination-1.0.8.dist-info/METADATA
weighted_combination-1.0.8.dist-info/WHEEL
weighted_combination-1.0.8.dist-info/licenses/LICENSE
weighted_combination-1.0.8.dist-info/RECORD
