Metadata-Version: 2.4
Name: Weighted_Combination
Version: 1.0.8
Summary: Uses a fully crystalline and fully amorphous endmember to calculate the amorphous fraction
Author-email: Will Gardner <wgardne9@vols.utk.edu>
License-Expression: MIT
License-File: LICENSE
Classifier: Operating System :: OS Independent
Classifier: Programming Language :: Python :: 3
Requires-Python: >=3.9
